slumber_serializers.py
slumber_serializers-0.1.0.dist-info/DESCRIPTION.rst
slumber_serializers-0.1.0.dist-info/METADATA
slumber_serializers-0.1.0.dist-info/RECORD
slumber_serializers-0.1.0.dist-info/WHEEL
slumber_serializers-0.1.0.dist-info/metadata.json
slumber_serializers-0.1.0.dist-info/top_level.txt
